coopstorage/__init__.py
coopstorage/eventDefinition.py
coopstorage/exceptions.py
coopstorage/location_search_prioritizers.py
coopstorage/logger.py
coopstorage/resolvers.py
coopstorage/state_generators.py
coopstorage/my_dataclasses/__init__.py
coopstorage/my_dataclasses/content.py
coopstorage/my_dataclasses/loc_inv_state.py
coopstorage/my_dataclasses/location.py
coopstorage/my_dataclasses/resource.py
coopstorage/my_dataclasses/resourceUom.py
coopstorage/my_dataclasses/storage_state.py
coopstorage/my_dataclasses/unitOfMeasure.py
coopstorage/my_dataclasses/uom_capacity.py
coopstorage/storage/__init__.py
coopstorage/storage/loc_inv_state_mutations.py
coopstorage/storage/loc_state_mutations.py
coopstorage/storage/storage.py
coopstorage/storage/storage_state_mutations.py
coopstorage-0.1.dist-info/METADATA
coopstorage-0.1.dist-info/WHEEL
coopstorage-0.1.dist-info/top_level.txt
coopstorage-0.1.dist-info/RECORD
