Metadata-Version: 2.1
Name: coopstorage
Version: 0.1
Summary: Package for embedded storage systems
Home-page: https://github.com/tylertjburns/coopstorage
Author: tburns
Author-email: tyler.tj.burns@gmail.com
License: MIT
Platform: UNKNOWN
Classifier: Development Status :: 3 - Alpha
Classifier: License :: OSI Approved :: MIT License
Classifier: Programming Language :: Python
Classifier: Programming Language :: Python :: 3.5
Classifier: Programming Language :: Python :: 3.6
Classifier: Topic :: Software Development :: Libraries
Classifier: Topic :: Software Development :: Libraries :: Python Modules
Classifier: Intended Audience :: Developers
Requires-Python: >3.5
Requires-Dist: aniso8601 (==9.0.1)
Requires-Dist: click (==8.1.3)
Requires-Dist: colorama (==0.4.4)
Requires-Dist: cooptools (==0.39)
Requires-Dist: Flask (==2.1.2)
Requires-Dist: Flask-RESTful (==0.3.9)
Requires-Dist: itsdangerous (==2.1.2)
Requires-Dist: Jinja2 (==3.1.2)
Requires-Dist: MarkupSafe (==2.1.1)
Requires-Dist: numpy (==1.22.4)
Requires-Dist: Pypubsub (==4.0.3)
Requires-Dist: pytz (==2022.1)
Requires-Dist: six (==1.16.0)
Requires-Dist: Werkzeug (==2.1.2)
